{
  "required": true,
  "minVersion": "0.8",
  "package": "subtick.mixins",
  "compatibilityLevel": "JAVA_8",
  "mixins": [
    "MinecraftServerMixin",
    "ServerLevelMixin",

    "carpet.ServerNetworkHandlerAccessor",
    "carpet.ServerNetworkHandlerMixin",
    "carpet.TickCommandMixin",

    "lithium.LithiumServerTickSchedulerAccessor"
  ],
  "client": [
    "client.ClientNetworkHandlerMixin",

    "client.ClientLevelMixin",
    "client.EntityMixin",
    "client.GuiMixin",
    "client.LevelRendererMixin"
  ],
  "injectors": {
    "defaultRequire": 1
  }
}
